fleetfind/__init__.py
fleetfind/apps.py
fleetfind/main.py
fleetfind-1.1.0.dist-info/METADATA
fleetfind-1.1.0.dist-info/WHEEL
fleetfind-1.1.0.dist-info/top_level.txt
fleetfind-1.1.0.dist-info/RECORD
