Metadata-Version: 2.1
Name: fleetfind
Version: 1.1.0
Summary: A Django package for searching across multiple models
Home-page: https://da-kodesio.github.io/fleetfind
Author: Aimé An-Nyong DEGBEY
Author-email: annyongdey19@gmail.com
Project-URL: Source, https://github.com/yourusername/fleetfind
Keywords: django search multi-model
Classifier: Development Status :: 3 - Alpha
Classifier: Intended Audience :: Developers
Classifier: License :: OSI Approved :: MIT License
Classifier: Programming Language :: Python :: 3
Classifier: Programming Language :: Python :: 3.6
Classifier: Programming Language :: Python :: 3.7
Classifier: Programming Language :: Python :: 3.8
Classifier: Programming Language :: Python :: 3.9
Classifier: Programming Language :: Python :: 3.10
Classifier: Programming Language :: Python :: 3.11
Requires-Python: >=3.6
Requires-Dist: django >=2.2
